dbTable.py
dbTable-0.0.4.dist-info/DESCRIPTION.rst
dbTable-0.0.4.dist-info/METADATA
dbTable-0.0.4.dist-info/RECORD
dbTable-0.0.4.dist-info/WHEEL
dbTable-0.0.4.dist-info/metadata.json
dbTable-0.0.4.dist-info/top_level.txt
