Metadata-Version: 2.0
Name: dbTable
Version: 0.0.4
Summary: A library to provide Table data constructs over SQLite Databases
Home-page: https://github.com/dibyaghosh/dbTable
Author: Dibya Ghosh
Author-email: dibya.ghosh@berkeley.edu
License: MIT
Keywords: datascience data science numpy database sqlite table column
Platform: UNKNOWN
Classifier: Development Status :: 3 - Alpha
Classifier: Intended Audience :: Developers
Classifier: Intended Audience :: Science/Research
Classifier: Topic :: Database :: Front-Ends
Classifier: Topic :: Database
Classifier: Topic :: Scientific/Engineering :: Mathematics
Classifier: Topic :: Scientific/Engineering
Classifier: Topic :: Scientific/Engineering :: Information Analysis
Classifier: License :: OSI Approved :: MIT License
Classifier: Programming Language :: Python :: 3
Classifier: Programming Language :: Python :: 3.2
Classifier: Programming Language :: Python :: 3.3
Classifier: Programming Language :: Python :: 3.4
Classifier: Programming Language :: Python :: 3.5
Classifier: Programming Language :: Python :: 3 :: Only
Requires-Dist: numpy
Requires-Dist: tabulate
Provides-Extra: dev
Requires-Dist: datascience; extra == 'dev'
Requires-Dist: pandas; extra == 'dev'
